errmod/__init__.py
errmod-0.1.1.dist-info/WHEEL
errmod-0.1.1.dist-info/METADATA
errmod-0.1.1.dist-info/RECORD
