Metadata-Version: 2.1
Name: errmod
Version: 0.1.1
Summary: String stuff
Author: Your Name
Author-email: you@example.com
Requires-Python: >=3.10,<4.0
Classifier: Programming Language :: Python :: 3
Classifier: Programming Language :: Python :: 3.10
